{
	"backtraceGraph" : 
	{
		"commands" : 
		[
			"install",
			"build_lib"
		],
		"files" : 
		[
			"build-support/custom-modules/ns3-module-macros.cmake",
			"src/csma-layout/CMakeLists.txt"
		],
		"nodes" : 
		[
			{
				"file" : 1
			},
			{
				"command" : 1,
				"file" : 1,
				"line" : 1,
				"parent" : 0
			},
			{
				"command" : 0,
				"file" : 0,
				"line" : 481,
				"parent" : 1
			}
		]
	},
	"installers" : 
	[
		{
			"backtrace" : 2,
			"component" : "Unspecified",
			"destination" : "lib",
			"paths" : 
			[
				"lib/libns3.42-csma-layout-debug.so"
			],
			"targetId" : "libcsma-layout::@48fc5a83301e8b2154b7",
			"targetIndex" : 126,
			"type" : "target"
		},
		{
			"backtrace" : 2,
			"component" : "Unspecified",
			"destination" : "include/ns3",
			"paths" : 
			[
				"src/csma-layout/model/csma-star-helper.h",
				"build/include/ns3/csma-layout-module.h"
			],
			"type" : "file"
		}
	],
	"paths" : 
	{
		"build" : "src/csma-layout",
		"source" : "src/csma-layout"
	}
}
